xreport/__init__.py
xreport/pipeline.py
xreport/report.py
xreport/utils.py
xreport/stages/__init__.py
xreport/stages/add_column_stage.py
xreport/stages/base_stage.py
xreport/stages/data_quality_stage.py
xreport/stages/drop_duplicate_stage.py
xreport/stages/expand_stage.py
xreport/stages/filter_stage.py
xreport/stages/groupby_stage.py
xreport/stages/map_stage.py
xreport/stages/projection_stage.py
xreport/stages/rename_stage.py
xreport/stages/source_stage.py
x_report-0.1.15.dist-info/LICENSE
x_report-0.1.15.dist-info/METADATA
x_report-0.1.15.dist-info/WHEEL
x_report-0.1.15.dist-info/top_level.txt
x_report-0.1.15.dist-info/RECORD
