Metadata-Version: 2.1
Name: x-report
Version: 0.1.15
Summary: Create a pipeline to generate reports with a visual description of each extraction and transformation phase.
Home-page: https://github.com/gaborando/x-report
Author: Gabor Galazzo
Author-email: gabor.galazzo@gmail.com
License: MIT
Classifier: Programming Language :: Python :: 3
Classifier: License :: OSI Approved :: MIT License
Classifier: Operating System :: OS Independent
Requires-Python: >=3.6
License-File: LICENSE
Requires-Dist: pandas
Requires-Dist: jinja2
